cvi/__init__.py
cvi/compat/__init__.py
cvi/compat/v0.py
cvi/modules/CH.py
cvi/modules/DB.py
cvi/modules/GD43.py
cvi/modules/GD53.py
cvi/modules/PS.py
cvi/modules/WB.py
cvi/modules/XB.py
cvi/modules/__init__.py
cvi/modules/_base.py
cvi/modules/cSIL.py
cvi/modules/rCIP.py
cvi-0.6.0.dist-info/LICENSE
cvi-0.6.0.dist-info/METADATA
cvi-0.6.0.dist-info/WHEEL
cvi-0.6.0.dist-info/top_level.txt
cvi-0.6.0.dist-info/RECORD
