Metadata-Version: 2.1
Name: cvi
Version: 0.6.0
Summary: A Python package for both batch and incremental cluster validity indices.
Author-email: Sasha Petrenko <petrenkos@mst.edu>
Maintainer-email: Sasha Petrenko <petrenkos@mst.edu>
License: MIT License
Project-URL: Homepage, https://github.com/AP6YC/cvi
Project-URL: Bug Reports, https://github.com/AP6YC/cvi/issues
Project-URL: Documentation, https://cluster-validity-indices.readthedocs.io/
Project-URL: Source, https://github.com/AP6YC/cvi/
Keywords: cluster validity indices,cluster validity index,incremental cluster validity indices,incremental cluster validity index,cluster validation,cvi,icvi
Classifier: Development Status :: 4 - Beta
Classifier: Intended Audience :: Developers
Classifier: Topic :: Software Development :: Build Tools
Classifier: License :: OSI Approved :: MIT License
Classifier: Programming Language :: Python :: 3
Classifier: Programming Language :: Python :: 3.6
Classifier: Programming Language :: Python :: 3.7
Classifier: Programming Language :: Python :: 3.8
Classifier: Programming Language :: Python :: 3.9
Classifier: Programming Language :: Python :: 3.10
Classifier: Programming Language :: Python :: 3.11
Classifier: Programming Language :: Python :: 3.12
Classifier: Programming Language :: Python :: 3 :: Only
Requires-Python: >=3.6
License-File: LICENSE
Requires-Dist: numpy
Provides-Extra: dev
Requires-Dist: check-manifest ; extra == 'dev'
Requires-Dist: build ; extra == 'dev'
Requires-Dist: setuptools ; extra == 'dev'
Requires-Dist: twine ; extra == 'dev'
Requires-Dist: jupyterlab ; extra == 'dev'
Provides-Extra: docs
Requires-Dist: sphinx ; extra == 'docs'
Requires-Dist: furo ; extra == 'docs'
Requires-Dist: sphinx-multiversion ; extra == 'docs'
Provides-Extra: test
Requires-Dist: pytest ; extra == 'test'
Requires-Dist: pytest-cov ; extra == 'test'
Requires-Dist: coverage ; extra == 'test'
Requires-Dist: pandas ; extra == 'test'
Requires-Dist: scikit-learn ; extra == 'test'
Requires-Dist: flake8 ; extra == 'test'
